{
    "name": "@ohos/devicesecuritylevel",
    "description": "openharmony's device security level management",
    "version": "3.0.0",
    "license": "Apache License 2.0",
    "publishAs": "code-segment",
    "segment": {
        "destpath": "base/security/devicesecuritylevel"
    },
    "dirs": {},
    "scripts": {
        "install": "DEST_PATH=${DEP_BUNDLE_BASE}/base/security/devicesecuritylevel && mkdir -p $DEST_PATH && cp -r ./* $DEST_PATH"
    },
    "author": {},
    "repository": "",
    "component": {
        "name": "devicesecuritylevel",
        "subsystem": "security",
        "syscap": [
            ""
        ],
        "features": [
            "devicesecuritylevel_dslm"
        ],
        "adapted_system_type": [
            "standard"
        ],
        "rom": "200KB",
        "ram": "2500KB",
        "deps": {
            "components": [
                "ipc_core",
                "libhilog",
                "samgr_proxy",
                "softbus_client",
                "utils"
            ],
            "third_party": [
                "cjson_static",
                "libcrypto"
            ]
        },
        "build": {
            "sub_component": [
                "//base/security/devicesecuritylevel/interfaces:dslm_sdk",
                "//base/security/devicesecuritylevel/oem_property/ohos:dslm_service",
                "//base/security/devicesecuritylevel/profile:dslm_service.rc"
            ],
            "inner_kits": [
                {
                    "name": "//base/security/devicesecuritylevel/interfaces:dslm_sdk",
                    "header": {
                        "header_files": [
                            "device_security_info.h",
                            "device_security_defines.h"
                        ],
                        "header_base": "//base/security/devicesecuritylevel/interfaces/include"
                    }
                }
            ],
            "test": [
                "//base/security/devicesecuritylevel/test:dslm_test"
            ]
        }
    }
}